sqlalchemy_create_table_as/__init__.py
sqlalchemy_create_table_as/create_table.py
sqlalchemy_create_table_as/create_table.pyi
sqlalchemy_create_table_as-0.3.0.dist-info/METADATA
sqlalchemy_create_table_as-0.3.0.dist-info/WHEEL
sqlalchemy_create_table_as-0.3.0.dist-info/LICENSE
sqlalchemy_create_table_as-0.3.0.dist-info/RECORD
